[
  {
    "meta": {
      "author": {
        "name": "Alice Bobbera",
        "email": "a@b.it"
      },
      "created": "2018-02-03T12:13:14Z",
      "tags": [
        "drama",
        "queen"
      ]
    },
    "title": "UI components for Dummies",
    "content": "Sed doloribus molestias voluptatem ut delectus vitae quo eum. Ut praesentium sed omnis sequi rerum praesentium aperiam modi. Occaecati voluptatum quis vel facere quis quisquam."
  },
  {
    "meta": {
      "author": {
        "name": "Alice Bobbera",
        "email": "a@b.it"
      },
      "created": "2018-02-03T12:13:14Z",
      "tags": [
        "drama",
        "queen"
      ]
    },
    "title": "UI components for Dummies",
    "content": "Sed doloribus molestias voluptatem ut delectus vitae quo eum. Ut praesentium sed omnis sequi rerum praesentium aperiam modi. Occaecati voluptatum quis vel facere quis quisquam."
  },
  {
    "meta": {
      "author": {
        "name": "Alice Bobbera",
        "email": "a@b.it"
      },
      "created": "2018-02-03T12:13:14Z",
      "tags": [
        "drama",
        "queen"
      ]
    },
    "title": "UI components for Dummies",
    "content": "Sed doloribus molestias voluptatem ut delectus vitae quo eum. Ut praesentium sed omnis sequi rerum praesentium aperiam modi. Occaecati voluptatum quis vel facere quis quisquam."
  },
  {
    "meta": {
      "author": {
        "name": "Alice Bobbera",
        "email": "a@b.it"
      },
      "created": "2018-02-03T12:13:14Z",
      "tags": [
        "drama",
        "queen"
      ]
    },
    "title": "UI components for Dummies",
    "content": "Sed doloribus molestias voluptatem ut delectus vitae quo eum. Ut praesentium sed omnis sequi rerum praesentium aperiam modi. Occaecati voluptatum quis vel facere quis quisquam."
  },
  {
    "meta": {
      "author": {
        "name": "Alice Bobbera",
        "email": "a@b.it"
      },
      "created": "2018-02-03T12:13:14Z",
      "tags": [
        "drama",
        "queen"
      ]
    },
    "title": "UI components for Dummies",
    "content": "Sed doloribus molestias voluptatem ut delectus vitae quo eum. Ut praesentium sed omnis sequi rerum praesentium aperiam modi. Occaecati voluptatum quis vel facere quis quisquam."
  },
  {
    "meta": {
      "author": {
        "name": "Charlie Doran",
        "email": "c@d.es"
      },
      "created": "2018-02-02T01:23:45Z",
      "tags": [
        "simplicity",
        "rules"
      ]
    },
    "title": "Look ma, so simple",
    "content": "Ratione necessitatibus doloremque itaque. Nihil hic alias cumque beatae esse sapiente incidunt. Illum vel eveniet officia."
  }
]